{
  "minecraft:recipes/food/bread": {
    "criteria": {
      "has_wheat": "2025-03-07 15:21:54 +0000"
    },
    "done": true
  },
  "minecraft:husbandry/plant_seed": {
    "criteria": {
      "wheat": "2025-03-07 15:22:09 +0000"
    },
    "done": true
  },
  "minecraft:end/root": {
    "criteria": {
      "entered_end": "2025-03-07 15:20:41 +0000"
    },
    "done": true
  },
  "minecraft:recipes/building_blocks/hay_block": {
    "criteria": {
      "has_wheat": "2025-03-07 15:21:54 +0000"
    },
    "done": true
  },
  "minecraft:adventure/adventuring_time": {
    "criteria": {
      "minecraft:forest": "2025-03-07 15:19:02 +0000",
      "minecraft:badlands": "2025-03-07 15:20:25 +0000",
      "minecraft:plains": "2025-03-07 15:18:52 +0000"
    },
    "done": false
  },
  "minecraft:story/enter_the_end": {
    "criteria": {
      "entered_end": "2025-03-07 15:20:41 +0000"
    },
    "done": true
  },
  "DataVersion": 2730
}